{
  "name": "core",
  "rules": {
    "source_file": {
      "type": "REPEAT",
      "content": {
        "type": "SYMBOL",
        "name": "_definition"
      }
    },
    "comment": {
      "type": "TOKEN",
      "content": {
        "type": "CHOICE",
        "members": [
          {
            "type": "SEQ",
            "members": [
              {
                "type": "STRING",
                "value": "//"
              },
              {
                "type": "PATTERN",
                "value": "[^\\n]*"
              }
            ]
          },
          {
            "type": "SEQ",
            "members": [
              {
                "type": "STRING",
                "value": "/*"
              },
              {
                "type": "PATTERN",
                "value": "[^*]*\\*+([^/*][^*]*\\*+)*"
              },
              {
                "type": "STRING",
                "value": "/"
              }
            ]
          }
        ]
      }
    },
    "_definition": {
      "type": "CHOICE",
      "members": [
        {
          "type": "SYMBOL",
          "name": "function_definition"
        },
        {
          "type": "SYMBOL",
          "name": "struct_definition"
        },
        {
          "type": "SYMBOL",
          "name": "enum_definition"
        },
        {
          "type": "SYMBOL",
          "name": "impl_definition"
        },
        {
          "type": "SYMBOL",
          "name": "flow_definition"
        },
        {
          "type": "SYMBOL",
          "name": "interface_definition"
        },
        {
          "type": "SYMBOL",
          "name": "type_definition"
        },
        {
          "type": "SYMBOL",
          "name": "import_declaration"
        },
        {
          "type": "SYMBOL",
          "name": "fileid_declaration"
        }
      ]
    },
    "function_definition": {
      "type": "SEQ",
      "members": [
        {
          "type": "STRING",
          "value": "fn"
        },
        {
          "type": "SYMBOL",
          "name": "identifier"
        },
        {
          "type": "SYMBOL",
          "name": "parameter_list"
        },
        {
          "type": "CHOICE",
          "members": [
            {
              "type": "SEQ",
              "members": [
                {
                  "type": "STRING",
                  "value": "->"
                },
                {
                  "type": "SYMBOL",
                  "name": "type"
                }
              ]
            },
            {
              "type": "BLANK"
            }
          ]
        },
        {
          "type": "SYMBOL",
          "name": "block"
        }
      ]
    },
    "flow_definition": {
      "type": "SEQ",
      "members": [
        {
          "type": "STRING",
          "value": "flow"
        },
        {
          "type": "SYMBOL",
          "name": "identifier"
        },
        {
          "type": "SYMBOL",
          "name": "parameter_list"
        },
        {
          "type": "CHOICE",
          "members": [
            {
              "type": "SEQ",
              "members": [
                {
                  "type": "STRING",
                  "value": "->"
                },
                {
                  "type": "SYMBOL",
                  "name": "type"
                }
              ]
            },
            {
              "type": "BLANK"
            }
          ]
        },
        {
          "type": "SYMBOL",
          "name": "block"
        }
      ]
    },
    "parameter_list": {
      "type": "SEQ",
      "members": [
        {
          "type": "STRING",
          "value": "("
        },
        {
          "type": "CHOICE",
          "members": [
            {
              "type": "CHOICE",
              "members": [
                {
                  "type": "SEQ",
                  "members": [
                    {
                      "type": "SYMBOL",
                      "name": "parameter"
                    },
                    {
                      "type": "REPEAT",
                      "content": {
                        "type": "SEQ",
                        "members": [
                          {
                            "type": "STRING",
                            "value": ","
                          },
                          {
                            "type": "SYMBOL",
                            "name": "parameter"
                          }
                        ]
                      }
                    }
                  ]
                },
                {
                  "type": "BLANK"
                }
              ]
            },
            {
              "type": "BLANK"
            }
          ]
        },
        {
          "type": "STRING",
          "value": ")"
        }
      ]
    },
    "parameter": {
      "type": "SEQ",
      "members": [
        {
          "type": "SYMBOL",
          "name": "identifier"
        },
        {
          "type": "CHOICE",
          "members": [
            {
              "type": "SEQ",
              "members": [
                {
                  "type": "STRING",
                  "value": ":"
                },
                {
                  "type": "SYMBOL",
                  "name": "type"
                }
              ]
            },
            {
              "type": "BLANK"
            }
          ]
        }
      ]
    },
    "struct_definition": {
      "type": "SEQ",
      "members": [
        {
          "type": "STRING",
          "value": "struct"
        },
        {
          "type": "SYMBOL",
          "name": "identifier"
        },
        {
          "type": "CHOICE",
          "members": [
            {
              "type": "SYMBOL",
              "name": "type_arguments"
            },
            {
              "type": "BLANK"
            }
          ]
        },
        {
          "type": "STRING",
          "value": "{"
        },
        {
          "type": "CHOICE",
          "members": [
            {
              "type": "CHOICE",
              "members": [
                {
                  "type": "SEQ",
                  "members": [
                    {
                      "type": "SYMBOL",
                      "name": "field_declaration"
                    },
                    {
                      "type": "REPEAT",
                      "content": {
                        "type": "SEQ",
                        "members": [
                          {
                            "type": "STRING",
                            "value": ","
                          },
                          {
                            "type": "SYMBOL",
                            "name": "field_declaration"
                          }
                        ]
                      }
                    }
                  ]
                },
                {
                  "type": "BLANK"
                }
              ]
            },
            {
              "type": "BLANK"
            }
          ]
        },
        {
          "type": "STRING",
          "value": "}"
        }
      ]
    },
    "field_declaration": {
      "type": "SEQ",
      "members": [
        {
          "type": "SYMBOL",
          "name": "identifier"
        },
        {
          "type": "STRING",
          "value": ":"
        },
        {
          "type": "SYMBOL",
          "name": "type"
        }
      ]
    },
    "enum_definition": {
      "type": "SEQ",
      "members": [
        {
          "type": "STRING",
          "value": "enum"
        },
        {
          "type": "SYMBOL",
          "name": "identifier"
        },
        {
          "type": "CHOICE",
          "members": [
            {
              "type": "SYMBOL",
              "name": "type_arguments"
            },
            {
              "type": "BLANK"
            }
          ]
        },
        {
          "type": "STRING",
          "value": "{"
        },
        {
          "type": "CHOICE",
          "members": [
            {
              "type": "CHOICE",
              "members": [
                {
                  "type": "SEQ",
                  "members": [
                    {
                      "type": "SYMBOL",
                      "name": "variant"
                    },
                    {
                      "type": "REPEAT",
                      "content": {
                        "type": "SEQ",
                        "members": [
                          {
                            "type": "STRING",
                            "value": ","
                          },
                          {
                            "type": "SYMBOL",
                            "name": "variant"
                          }
                        ]
                      }
                    }
                  ]
                },
                {
                  "type": "BLANK"
                }
              ]
            },
            {
              "type": "BLANK"
            }
          ]
        },
        {
          "type": "STRING",
          "value": "}"
        }
      ]
    },
    "variant": {
      "type": "SEQ",
      "members": [
        {
          "type": "SYMBOL",
          "name": "identifier"
        },
        {
          "type": "CHOICE",
          "members": [
            {
              "type": "SEQ",
              "members": [
                {
                  "type": "STRING",
                  "value": "("
                },
                {
                  "type": "CHOICE",
                  "members": [
                    {
                      "type": "SEQ",
                      "members": [
                        {
                          "type": "SYMBOL",
                          "name": "type"
                        },
                        {
                          "type": "REPEAT",
                          "content": {
                            "type": "SEQ",
                            "members": [
                              {
                                "type": "STRING",
                                "value": ","
                              },
                              {
                                "type": "SYMBOL",
                                "name": "type"
                              }
                            ]
                          }
                        }
                      ]
                    },
                    {
                      "type": "BLANK"
                    }
                  ]
                },
                {
                  "type": "STRING",
                  "value": ")"
                }
              ]
            },
            {
              "type": "BLANK"
            }
          ]
        }
      ]
    },
    "interface_definition": {
      "type": "SEQ",
      "members": [
        {
          "type": "STRING",
          "value": "interface"
        },
        {
          "type": "SYMBOL",
          "name": "identifier"
        },
        {
          "type": "CHOICE",
          "members": [
            {
              "type": "SYMBOL",
              "name": "type_arguments"
            },
            {
              "type": "BLANK"
            }
          ]
        },
        {
          "type": "STRING",
          "value": "{"
        },
        {
          "type": "REPEAT",
          "content": {
            "type": "SYMBOL",
            "name": "method_signature"
          }
        },
        {
          "type": "STRING",
          "value": "}"
        }
      ]
    },
    "method_signature": {
      "type": "SEQ",
      "members": [
        {
          "type": "STRING",
          "value": "fn"
        },
        {
          "type": "SYMBOL",
          "name": "identifier"
        },
        {
          "type": "SYMBOL",
          "name": "parameter_list"
        },
        {
          "type": "CHOICE",
          "members": [
            {
              "type": "SEQ",
              "members": [
                {
                  "type": "STRING",
                  "value": "->"
                },
                {
                  "type": "SYMBOL",
                  "name": "type"
                }
              ]
            },
            {
              "type": "BLANK"
            }
          ]
        }
      ]
    },
    "impl_definition": {
      "type": "SEQ",
      "members": [
        {
          "type": "STRING",
          "value": "impl"
        },
        {
          "type": "SYMBOL",
          "name": "type"
        },
        {
          "type": "CHOICE",
          "members": [
            {
              "type": "SEQ",
              "members": [
                {
                  "type": "STRING",
                  "value": "for"
                },
                {
                  "type": "SYMBOL",
                  "name": "type"
                }
              ]
            },
            {
              "type": "BLANK"
            }
          ]
        },
        {
          "type": "STRING",
          "value": "{"
        },
        {
          "type": "REPEAT",
          "content": {
            "type": "SYMBOL",
            "name": "function_definition"
          }
        },
        {
          "type": "STRING",
          "value": "}"
        }
      ]
    },
    "type_definition": {
      "type": "SEQ",
      "members": [
        {
          "type": "STRING",
          "value": "type"
        },
        {
          "type": "SYMBOL",
          "name": "identifier"
        },
        {
          "type": "STRING",
          "value": "="
        },
        {
          "type": "SYMBOL",
          "name": "type"
        }
      ]
    },
    "import_declaration": {
      "type": "SEQ",
      "members": [
        {
          "type": "STRING",
          "value": "import"
        },
        {
          "type": "SYMBOL",
          "name": "identifier"
        },
        {
          "type": "CHOICE",
          "members": [
            {
              "type": "SEQ",
              "members": [
                {
                  "type": "STRING",
                  "value": ":"
                },
                {
                  "type": "SYMBOL",
                  "name": "identifier"
                }
              ]
            },
            {
              "type": "BLANK"
            }
          ]
        }
      ]
    },
    "fileid_declaration": {
      "type": "SEQ",
      "members": [
        {
          "type": "STRING",
          "value": "fileid"
        },
        {
          "type": "SYMBOL",
          "name": "string"
        }
      ]
    },
    "type": {
      "type": "CHOICE",
      "members": [
        {
          "type": "CHOICE",
          "members": [
            {
              "type": "STRING",
              "value": "int"
            },
            {
              "type": "STRING",
              "value": "float"
            },
            {
              "type": "STRING",
              "value": "bool"
            },
            {
              "type": "STRING",
              "value": "string"
            },
            {
              "type": "STRING",
              "value": "char"
            },
            {
              "type": "STRING",
              "value": "unit"
            },
            {
              "type": "STRING",
              "value": "never"
            },
            {
              "type": "STRING",
              "value": "auto"
            }
          ]
        },
        {
          "type": "SYMBOL",
          "name": "identifier"
        },
        {
          "type": "PREC_LEFT",
          "value": 1,
          "content": {
            "type": "SEQ",
            "members": [
              {
                "type": "SYMBOL",
                "name": "type"
              },
              {
                "type": "STRING",
                "value": "?"
              }
            ]
          }
        },
        {
          "type": "SEQ",
          "members": [
            {
              "type": "STRING",
              "value": "["
            },
            {
              "type": "SYMBOL",
              "name": "type"
            },
            {
              "type": "CHOICE",
              "members": [
                {
                  "type": "SEQ",
                  "members": [
                    {
                      "type": "STRING",
                      "value": ";"
                    },
                    {
                      "type": "SYMBOL",
                      "name": "expression"
                    }
                  ]
                },
                {
                  "type": "BLANK"
                }
              ]
            },
            {
              "type": "STRING",
              "value": "]"
            }
          ]
        },
        {
          "type": "SEQ",
          "members": [
            {
              "type": "STRING",
              "value": "("
            },
            {
              "type": "CHOICE",
              "members": [
                {
                  "type": "SEQ",
                  "members": [
                    {
                      "type": "SYMBOL",
                      "name": "type"
                    },
                    {
                      "type": "REPEAT",
                      "content": {
                        "type": "SEQ",
                        "members": [
                          {
                            "type": "STRING",
                            "value": ","
                          },
                          {
                            "type": "SYMBOL",
                            "name": "type"
                          }
                        ]
                      }
                    }
                  ]
                },
                {
                  "type": "BLANK"
                }
              ]
            },
            {
              "type": "STRING",
              "value": ")"
            }
          ]
        },
        {
          "type": "PREC_RIGHT",
          "value": 2,
          "content": {
            "type": "SEQ",
            "members": [
              {
                "type": "STRING",
                "value": "&"
              },
              {
                "type": "CHOICE",
                "members": [
                  {
                    "type": "STRING",
                    "value": "mut"
                  },
                  {
                    "type": "BLANK"
                  }
                ]
              },
              {
                "type": "SYMBOL",
                "name": "type"
              }
            ]
          }
        },
        {
          "type": "PREC_LEFT",
          "value": 0,
          "content": {
            "type": "SEQ",
            "members": [
              {
                "type": "SYMBOL",
                "name": "type"
              },
              {
                "type": "STRING",
                "value": "::"
              },
              {
                "type": "SYMBOL",
                "name": "identifier"
              }
            ]
          }
        }
      ]
    },
    "type_arguments": {
      "type": "SEQ",
      "members": [
        {
          "type": "STRING",
          "value": "["
        },
        {
          "type": "CHOICE",
          "members": [
            {
              "type": "SEQ",
              "members": [
                {
                  "type": "SYMBOL",
                  "name": "type"
                },
                {
                  "type": "REPEAT",
                  "content": {
                    "type": "SEQ",
                    "members": [
                      {
                        "type": "STRING",
                        "value": ","
                      },
                      {
                        "type": "SYMBOL",
                        "name": "type"
                      }
                    ]
                  }
                }
              ]
            },
            {
              "type": "BLANK"
            }
          ]
        },
        {
          "type": "STRING",
          "value": "]"
        }
      ]
    },
    "block": {
      "type": "SEQ",
      "members": [
        {
          "type": "STRING",
          "value": "{"
        },
        {
          "type": "REPEAT",
          "content": {
            "type": "SYMBOL",
            "name": "_statement"
          }
        },
        {
          "type": "STRING",
          "value": "}"
        }
      ]
    },
    "_statement": {
      "type": "CHOICE",
      "members": [
        {
          "type": "SYMBOL",
          "name": "let_declaration"
        },
        {
          "type": "SYMBOL",
          "name": "assignment"
        },
        {
          "type": "SYMBOL",
          "name": "return_statement"
        },
        {
          "type": "SYMBOL",
          "name": "expression"
        }
      ]
    },
    "let_declaration": {
      "type": "SEQ",
      "members": [
        {
          "type": "CHOICE",
          "members": [
            {
              "type": "SYMBOL",
              "name": "identifier"
            },
            {
              "type": "SEQ",
              "members": [
                {
                  "type": "SYMBOL",
                  "name": "identifier"
                },
                {
                  "type": "STRING",
                  "value": ","
                },
                {
                  "type": "SYMBOL",
                  "name": "identifier"
                }
              ]
            }
          ]
        },
        {
          "type": "CHOICE",
          "members": [
            {
              "type": "STRING",
              "value": ":="
            },
            {
              "type": "SEQ",
              "members": [
                {
                  "type": "STRING",
                  "value": ":"
                },
                {
                  "type": "CHOICE",
                  "members": [
                    {
                      "type": "SYMBOL",
                      "name": "type"
                    },
                    {
                      "type": "BLANK"
                    }
                  ]
                },
                {
                  "type": "STRING",
                  "value": "="
                }
              ]
            }
          ]
        },
        {
          "type": "SYMBOL",
          "name": "expression"
        },
        {
          "type": "CHOICE",
          "members": [
            {
              "type": "SEQ",
              "members": [
                {
                  "type": "STRING",
                  "value": ","
                },
                {
                  "type": "SYMBOL",
                  "name": "expression"
                }
              ]
            },
            {
              "type": "BLANK"
            }
          ]
        }
      ]
    },
    "assignment": {
      "type": "SEQ",
      "members": [
        {
          "type": "SYMBOL",
          "name": "expression"
        },
        {
          "type": "STRING",
          "value": "="
        },
        {
          "type": "SYMBOL",
          "name": "expression"
        }
      ]
    },
    "return_statement": {
      "type": "PREC_RIGHT",
      "value": 0,
      "content": {
        "type": "SEQ",
        "members": [
          {
            "type": "STRING",
            "value": "return"
          },
          {
            "type": "CHOICE",
            "members": [
              {
                "type": "SYMBOL",
                "name": "expression"
              },
              {
                "type": "BLANK"
              }
            ]
          }
        ]
      }
    },
    "expression": {
      "type": "CHOICE",
      "members": [
        {
          "type": "PREC",
          "value": 2,
          "content": {
            "type": "SYMBOL",
            "name": "binary_expression"
          }
        },
        {
          "type": "PREC",
          "value": 1,
          "content": {
            "type": "SYMBOL",
            "name": "unary_expression"
          }
        },
        {
          "type": "SYMBOL",
          "name": "if_expression"
        },
        {
          "type": "SYMBOL",
          "name": "match_expression"
        },
        {
          "type": "SYMBOL",
          "name": "loop_expression"
        },
        {
          "type": "SYMBOL",
          "name": "for_expression"
        },
        {
          "type": "SYMBOL",
          "name": "call_expression"
        },
        {
          "type": "SYMBOL",
          "name": "field_expression"
        },
        {
          "type": "SYMBOL",
          "name": "index_expression"
        },
        {
          "type": "SYMBOL",
          "name": "struct_literal"
        },
        {
          "type": "SYMBOL",
          "name": "go_expression"
        },
        {
          "type": "SYMBOL",
          "name": "await_expression"
        },
        {
          "type": "SYMBOL",
          "name": "recv_expression"
        },
        {
          "type": "SYMBOL",
          "name": "block"
        },
        {
          "type": "SYMBOL",
          "name": "identifier"
        },
        {
          "type": "SYMBOL",
          "name": "integer_literal"
        },
        {
          "type": "SYMBOL",
          "name": "float_literal"
        },
        {
          "type": "SYMBOL",
          "name": "string"
        },
        {
          "type": "SYMBOL",
          "name": "char_literal"
        },
        {
          "type": "CHOICE",
          "members": [
            {
              "type": "STRING",
              "value": "true"
            },
            {
              "type": "STRING",
              "value": "false"
            },
            {
              "type": "STRING",
              "value": "unit"
            },
            {
              "type": "STRING",
              "value": "None"
            }
          ]
        },
        {
          "type": "SYMBOL",
          "name": "tuple_expression"
        },
        {
          "type": "SYMBOL",
          "name": "array_expression"
        }
      ]
    },
    "if_expression": {
      "type": "SEQ",
      "members": [
        {
          "type": "STRING",
          "value": "if"
        },
        {
          "type": "SYMBOL",
          "name": "expression"
        },
        {
          "type": "SYMBOL",
          "name": "block"
        },
        {
          "type": "CHOICE",
          "members": [
            {
              "type": "SEQ",
              "members": [
                {
                  "type": "STRING",
                  "value": "else"
                },
                {
                  "type": "CHOICE",
                  "members": [
                    {
                      "type": "SYMBOL",
                      "name": "block"
                    },
                    {
                      "type": "SYMBOL",
                      "name": "if_expression"
                    }
                  ]
                }
              ]
            },
            {
              "type": "BLANK"
            }
          ]
        }
      ]
    },
    "match_expression": {
      "type": "SEQ",
      "members": [
        {
          "type": "STRING",
          "value": "match"
        },
        {
          "type": "SYMBOL",
          "name": "expression"
        },
        {
          "type": "STRING",
          "value": "{"
        },
        {
          "type": "REPEAT",
          "content": {
            "type": "SYMBOL",
            "name": "match_arm"
          }
        },
        {
          "type": "STRING",
          "value": "}"
        }
      ]
    },
    "match_arm": {
      "type": "SEQ",
      "members": [
        {
          "type": "SYMBOL",
          "name": "pattern"
        },
        {
          "type": "STRING",
          "value": "=>"
        },
        {
          "type": "SYMBOL",
          "name": "expression"
        }
      ]
    },
    "pattern": {
      "type": "CHOICE",
      "members": [
        {
          "type": "SYMBOL",
          "name": "identifier"
        },
        {
          "type": "STRING",
          "value": "_"
        },
        {
          "type": "SEQ",
          "members": [
            {
              "type": "SYMBOL",
              "name": "identifier"
            },
            {
              "type": "STRING",
              "value": "("
            },
            {
              "type": "CHOICE",
              "members": [
                {
                  "type": "SEQ",
                  "members": [
                    {
                      "type": "SYMBOL",
                      "name": "pattern"
                    },
                    {
                      "type": "REPEAT",
                      "content": {
                        "type": "SEQ",
                        "members": [
                          {
                            "type": "STRING",
                            "value": ","
                          },
                          {
                            "type": "SYMBOL",
                            "name": "pattern"
                          }
                        ]
                      }
                    }
                  ]
                },
                {
                  "type": "BLANK"
                }
              ]
            },
            {
              "type": "STRING",
              "value": ")"
            }
          ]
        }
      ]
    },
    "loop_expression": {
      "type": "SEQ",
      "members": [
        {
          "type": "STRING",
          "value": "loop"
        },
        {
          "type": "SYMBOL",
          "name": "block"
        }
      ]
    },
    "for_expression": {
      "type": "SEQ",
      "members": [
        {
          "type": "STRING",
          "value": "for"
        },
        {
          "type": "SYMBOL",
          "name": "identifier"
        },
        {
          "type": "STRING",
          "value": "in"
        },
        {
          "type": "SYMBOL",
          "name": "expression"
        },
        {
          "type": "SYMBOL",
          "name": "block"
        }
      ]
    },
    "call_expression": {
      "type": "PREC",
      "value": 3,
      "content": {
        "type": "SEQ",
        "members": [
          {
            "type": "CHOICE",
            "members": [
              {
                "type": "SYMBOL",
                "name": "identifier"
              },
              {
                "type": "SYMBOL",
                "name": "field_expression"
              }
            ]
          },
          {
            "type": "STRING",
            "value": "("
          },
          {
            "type": "CHOICE",
            "members": [
              {
                "type": "CHOICE",
                "members": [
                  {
                    "type": "SEQ",
                    "members": [
                      {
                        "type": "SYMBOL",
                        "name": "expression"
                      },
                      {
                        "type": "REPEAT",
                        "content": {
                          "type": "SEQ",
                          "members": [
                            {
                              "type": "STRING",
                              "value": ","
                            },
                            {
                              "type": "SYMBOL",
                              "name": "expression"
                            }
                          ]
                        }
                      }
                    ]
                  },
                  {
                    "type": "BLANK"
                  }
                ]
              },
              {
                "type": "BLANK"
              }
            ]
          },
          {
            "type": "STRING",
            "value": ")"
          }
        ]
      }
    },
    "field_expression": {
      "type": "PREC",
      "value": 3,
      "content": {
        "type": "SEQ",
        "members": [
          {
            "type": "SYMBOL",
            "name": "expression"
          },
          {
            "type": "STRING",
            "value": "."
          },
          {
            "type": "SYMBOL",
            "name": "identifier"
          }
        ]
      }
    },
    "index_expression": {
      "type": "PREC",
      "value": 3,
      "content": {
        "type": "SEQ",
        "members": [
          {
            "type": "SYMBOL",
            "name": "expression"
          },
          {
            "type": "STRING",
            "value": "["
          },
          {
            "type": "SYMBOL",
            "name": "expression"
          },
          {
            "type": "STRING",
            "value": "]"
          }
        ]
      }
    },
    "struct_literal": {
      "type": "PREC",
      "value": 3,
      "content": {
        "type": "SEQ",
        "members": [
          {
            "type": "SYMBOL",
            "name": "identifier"
          },
          {
            "type": "STRING",
            "value": "{"
          },
          {
            "type": "CHOICE",
            "members": [
              {
                "type": "CHOICE",
                "members": [
                  {
                    "type": "SEQ",
                    "members": [
                      {
                        "type": "SEQ",
                        "members": [
                          {
                            "type": "SYMBOL",
                            "name": "identifier"
                          },
                          {
                            "type": "STRING",
                            "value": "="
                          },
                          {
                            "type": "SYMBOL",
                            "name": "expression"
                          }
                        ]
                      },
                      {
                        "type": "REPEAT",
                        "content": {
                          "type": "SEQ",
                          "members": [
                            {
                              "type": "STRING",
                              "value": ","
                            },
                            {
                              "type": "SEQ",
                              "members": [
                                {
                                  "type": "SYMBOL",
                                  "name": "identifier"
                                },
                                {
                                  "type": "STRING",
                                  "value": "="
                                },
                                {
                                  "type": "SYMBOL",
                                  "name": "expression"
                                }
                              ]
                            }
                          ]
                        }
                      }
                    ]
                  },
                  {
                    "type": "BLANK"
                  }
                ]
              },
              {
                "type": "BLANK"
              }
            ]
          },
          {
            "type": "STRING",
            "value": "}"
          }
        ]
      }
    },
    "go_expression": {
      "type": "PREC",
      "value": 5,
      "content": {
        "type": "SEQ",
        "members": [
          {
            "type": "STRING",
            "value": "go"
          },
          {
            "type": "SYMBOL",
            "name": "expression"
          }
        ]
      }
    },
    "await_expression": {
      "type": "PREC",
      "value": 5,
      "content": {
        "type": "SEQ",
        "members": [
          {
            "type": "STRING",
            "value": "await"
          },
          {
            "type": "SYMBOL",
            "name": "expression"
          }
        ]
      }
    },
    "recv_expression": {
      "type": "PREC",
      "value": 3,
      "content": {
        "type": "SEQ",
        "members": [
          {
            "type": "SYMBOL",
            "name": "identifier"
          },
          {
            "type": "STRING",
            "value": ".recv()"
          }
        ]
      }
    },
    "tuple_expression": {
      "type": "SEQ",
      "members": [
        {
          "type": "STRING",
          "value": "("
        },
        {
          "type": "CHOICE",
          "members": [
            {
              "type": "SEQ",
              "members": [
                {
                  "type": "SYMBOL",
                  "name": "expression"
                },
                {
                  "type": "REPEAT",
                  "content": {
                    "type": "SEQ",
                    "members": [
                      {
                        "type": "STRING",
                        "value": ","
                      },
                      {
                        "type": "SYMBOL",
                        "name": "expression"
                      }
                    ]
                  }
                }
              ]
            },
            {
              "type": "BLANK"
            }
          ]
        },
        {
          "type": "CHOICE",
          "members": [
            {
              "type": "STRING",
              "value": ","
            },
            {
              "type": "BLANK"
            }
          ]
        },
        {
          "type": "STRING",
          "value": ")"
        }
      ]
    },
    "array_expression": {
      "type": "SEQ",
      "members": [
        {
          "type": "STRING",
          "value": "["
        },
        {
          "type": "CHOICE",
          "members": [
            {
              "type": "SEQ",
              "members": [
                {
                  "type": "SYMBOL",
                  "name": "expression"
                },
                {
                  "type": "REPEAT",
                  "content": {
                    "type": "SEQ",
                    "members": [
                      {
                        "type": "STRING",
                        "value": ","
                      },
                      {
                        "type": "SYMBOL",
                        "name": "expression"
                      }
                    ]
                  }
                }
              ]
            },
            {
              "type": "BLANK"
            }
          ]
        },
        {
          "type": "STRING",
          "value": "]"
        }
      ]
    },
    "binary_expression": {
      "type": "CHOICE",
      "members": [
        {
          "type": "PREC_LEFT",
          "value": 1,
          "content": {
            "type": "SEQ",
            "members": [
              {
                "type": "SYMBOL",
                "name": "expression"
              },
              {
                "type": "STRING",
                "value": "+"
              },
              {
                "type": "SYMBOL",
                "name": "expression"
              }
            ]
          }
        },
        {
          "type": "PREC_LEFT",
          "value": 1,
          "content": {
            "type": "SEQ",
            "members": [
              {
                "type": "SYMBOL",
                "name": "expression"
              },
              {
                "type": "STRING",
                "value": "-"
              },
              {
                "type": "SYMBOL",
                "name": "expression"
              }
            ]
          }
        },
        {
          "type": "PREC_LEFT",
          "value": 2,
          "content": {
            "type": "SEQ",
            "members": [
              {
                "type": "SYMBOL",
                "name": "expression"
              },
              {
                "type": "STRING",
                "value": "*"
              },
              {
                "type": "SYMBOL",
                "name": "expression"
              }
            ]
          }
        },
        {
          "type": "PREC_LEFT",
          "value": 2,
          "content": {
            "type": "SEQ",
            "members": [
              {
                "type": "SYMBOL",
                "name": "expression"
              },
              {
                "type": "STRING",
                "value": "/"
              },
              {
                "type": "SYMBOL",
                "name": "expression"
              }
            ]
          }
        },
        {
          "type": "PREC_LEFT",
          "value": 2,
          "content": {
            "type": "SEQ",
            "members": [
              {
                "type": "SYMBOL",
                "name": "expression"
              },
              {
                "type": "STRING",
                "value": "%"
              },
              {
                "type": "SYMBOL",
                "name": "expression"
              }
            ]
          }
        },
        {
          "type": "PREC_LEFT",
          "value": 0,
          "content": {
            "type": "SEQ",
            "members": [
              {
                "type": "SYMBOL",
                "name": "expression"
              },
              {
                "type": "STRING",
                "value": "=="
              },
              {
                "type": "SYMBOL",
                "name": "expression"
              }
            ]
          }
        },
        {
          "type": "PREC_LEFT",
          "value": 0,
          "content": {
            "type": "SEQ",
            "members": [
              {
                "type": "SYMBOL",
                "name": "expression"
              },
              {
                "type": "STRING",
                "value": "!="
              },
              {
                "type": "SYMBOL",
                "name": "expression"
              }
            ]
          }
        },
        {
          "type": "PREC_LEFT",
          "value": 0,
          "content": {
            "type": "SEQ",
            "members": [
              {
                "type": "SYMBOL",
                "name": "expression"
              },
              {
                "type": "STRING",
                "value": "<"
              },
              {
                "type": "SYMBOL",
                "name": "expression"
              }
            ]
          }
        },
        {
          "type": "PREC_LEFT",
          "value": 0,
          "content": {
            "type": "SEQ",
            "members": [
              {
                "type": "SYMBOL",
                "name": "expression"
              },
              {
                "type": "STRING",
                "value": ">"
              },
              {
                "type": "SYMBOL",
                "name": "expression"
              }
            ]
          }
        },
        {
          "type": "PREC_LEFT",
          "value": 0,
          "content": {
            "type": "SEQ",
            "members": [
              {
                "type": "SYMBOL",
                "name": "expression"
              },
              {
                "type": "STRING",
                "value": "<="
              },
              {
                "type": "SYMBOL",
                "name": "expression"
              }
            ]
          }
        },
        {
          "type": "PREC_LEFT",
          "value": 0,
          "content": {
            "type": "SEQ",
            "members": [
              {
                "type": "SYMBOL",
                "name": "expression"
              },
              {
                "type": "STRING",
                "value": ">="
              },
              {
                "type": "SYMBOL",
                "name": "expression"
              }
            ]
          }
        },
        {
          "type": "PREC_LEFT",
          "value": -1,
          "content": {
            "type": "SEQ",
            "members": [
              {
                "type": "SYMBOL",
                "name": "expression"
              },
              {
                "type": "STRING",
                "value": "&&"
              },
              {
                "type": "SYMBOL",
                "name": "expression"
              }
            ]
          }
        },
        {
          "type": "PREC_LEFT",
          "value": -2,
          "content": {
            "type": "SEQ",
            "members": [
              {
                "type": "SYMBOL",
                "name": "expression"
              },
              {
                "type": "STRING",
                "value": "||"
              },
              {
                "type": "SYMBOL",
                "name": "expression"
              }
            ]
          }
        }
      ]
    },
    "unary_expression": {
      "type": "PREC",
      "value": 4,
      "content": {
        "type": "SEQ",
        "members": [
          {
            "type": "CHOICE",
            "members": [
              {
                "type": "STRING",
                "value": "-"
              },
              {
                "type": "STRING",
                "value": "!"
              },
              {
                "type": "STRING",
                "value": "&"
              },
              {
                "type": "STRING",
                "value": "&mut"
              }
            ]
          },
          {
            "type": "SYMBOL",
            "name": "expression"
          }
        ]
      }
    },
    "identifier": {
      "type": "PATTERN",
      "value": "[a-zA-Z_][a-zA-Z0-9_]*"
    },
    "integer_literal": {
      "type": "TOKEN",
      "content": {
        "type": "CHOICE",
        "members": [
          {
            "type": "PATTERN",
            "value": "[0-9][0-9_]*"
          },
          {
            "type": "SEQ",
            "members": [
              {
                "type": "STRING",
                "value": "0x"
              },
              {
                "type": "PATTERN",
                "value": "[0-9a-fA-F][0-9a-fA-F_]*"
              }
            ]
          },
          {
            "type": "SEQ",
            "members": [
              {
                "type": "STRING",
                "value": "0o"
              },
              {
                "type": "PATTERN",
                "value": "[0-7][0-7_]*"
              }
            ]
          },
          {
            "type": "SEQ",
            "members": [
              {
                "type": "STRING",
                "value": "0b"
              },
              {
                "type": "PATTERN",
                "value": "[01][01_]*"
              }
            ]
          }
        ]
      }
    },
    "float_literal": {
      "type": "TOKEN",
      "content": {
        "type": "SEQ",
        "members": [
          {
            "type": "PATTERN",
            "value": "[0-9][0-9_]*"
          },
          {
            "type": "STRING",
            "value": "."
          },
          {
            "type": "PATTERN",
            "value": "[0-9][0-9_]*"
          },
          {
            "type": "CHOICE",
            "members": [
              {
                "type": "PATTERN",
                "value": "[eE][+-]?[0-9]+"
              },
              {
                "type": "BLANK"
              }
            ]
          }
        ]
      }
    },
    "string": {
      "type": "TOKEN",
      "content": {
        "type": "SEQ",
        "members": [
          {
            "type": "STRING",
            "value": "\""
          },
          {
            "type": "REPEAT",
            "content": {
              "type": "CHOICE",
              "members": [
                {
                  "type": "PATTERN",
                  "value": "[^\"\\\\]"
                },
                {
                  "type": "PATTERN",
                  "value": "\\\\."
                }
              ]
            }
          },
          {
            "type": "STRING",
            "value": "\""
          }
        ]
      }
    },
    "char_literal": {
      "type": "TOKEN",
      "content": {
        "type": "SEQ",
        "members": [
          {
            "type": "STRING",
            "value": "'"
          },
          {
            "type": "CHOICE",
            "members": [
              {
                "type": "PATTERN",
                "value": "[^'\\\\]"
              },
              {
                "type": "PATTERN",
                "value": "\\\\."
              }
            ]
          },
          {
            "type": "STRING",
            "value": "'"
          }
        ]
      }
    }
  },
  "extras": [
    {
      "type": "PATTERN",
      "value": "\\s"
    },
    {
      "type": "SYMBOL",
      "name": "comment"
    },
    {
      "type": "STRING",
      "value": ";"
    }
  ],
  "conflicts": [
    [
      "type",
      "expression"
    ],
    [
      "call_expression",
      "struct_literal"
    ],
    [
      "go_expression",
      "binary_expression"
    ],
    [
      "go_expression",
      "call_expression"
    ]
  ],
  "precedences": [],
  "externals": [],
  "inline": [],
  "supertypes": [
    "expression",
    "_statement"
  ]
}
